{
  "users": [
    {
      "login": "die",
      "password": "please",
      "tweets": [],
      "userId": "api",
      "id": 1
    },
    {
      "login": "die1",
      "password": "123",
      "tweets": [],
      "userId": "api",
      "id": 2
    },
    {
      "login": "112223",
      "password": "11111",
      "tweets": [],
      "id": 3
    },
    {
      "login": "Adeon18",
      "password": "qqqqq",
      "tweets": [],
      "id": 4
    },
    {
      "login": "dd",
      "password": "dddd",
      "tweets": [],
      "id": 5
    },
    {
      "login": "ddddd",
      "password": "[1543023191,-61183035,1205784348,-958700559,233526691,-960110775,2103648179,-648144193]",
      "tweets": [],
      "id": 6
    },
    {
      "login": "please",
      "password": "[735746893,-72614479,2094484866,2003360337,-1733416063,1426074185,1160035306,-151663174]",
      "tweets": [],
      "id": 7
    },
    {
      "login": "ssss",
      "password": "[2083441927,-246061948,836827467,-1994097295,1012369121,-415328961,803728547,-1791701651]",
      "tweets": [],
      "id": 8
    }
  ]
}